setup.cfg
setup.py
./bkapi/__init__.py
./bkapi/paasv3/__init__.py
./bkapi/paasv3/client.py
./bkapi/paasv3/client.pyi
./bkapi/paasv3/shortcuts.py
./bkapigw/__init__.py
./bkapigw/paasv3/__init__.py
./bkapigw/paasv3/base.py
./bkapigw/paasv3/client.py
./bkapigw/paasv3/conf.py
./bkapigw/paasv3/exceptions.py
./bkapigw/paasv3/resources.py
./bkapigw/paasv3/shortcuts.py
./bkapigw/paasv3/utils.py
bkapi_paasv3.egg-info/PKG-INFO
bkapi_paasv3.egg-info/SOURCES.txt
bkapi_paasv3.egg-info/dependency_links.txt
bkapi_paasv3.egg-info/namespace_packages.txt
bkapi_paasv3.egg-info/requires.txt
bkapi_paasv3.egg-info/top_level.txt