Metadata-Version: 2.1
Name: bkapi-paasv3
Version: 1.0.1
Summary: 蓝鲸 PaaS 平台 - 开发者中心
Home-page: UNKNOWN
Author: blueking
License: Apach License 2.0
Platform: UNKNOWN
Requires-Python: !=3.0.*,!=3.1.*,!=3.2.*,!=3.3.*,!=3.4.*,!=3.5.*,<4.0,>=2.7
Provides-Extra: django
